seo_agent/__init__.py
seo_agent/__main__.py
seo_agent/analyzer.py
seo_agent/audit.py
seo_agent/baseline.py
seo_agent/cli.py
seo_agent/config.py
seo_agent/constants.py
seo_agent/models.py
seo_agent/network.py
seo_agent/reporting.py
seo_agent/robots.py
seo_agent/checks/__init__.py
seo_agent/checks/broken_links.py
seo_agent/checks/canonical.py
seo_agent/checks/crawlability.py
seo_agent/checks/document.py
seo_agent/checks/fetch.py
seo_agent/checks/html.py
seo_agent/checks/links.py
seo_agent/checks/meta.py
seo_agent/checks/performance.py
seo_agent/checks/redirects.py
seo_agent/checks/registry.py
seo_agent/checks/schema.py
seo_agent/checks/security.py
seo_agent/checks/status_and_headers.py
seo_agent/checks/types.py
seo_agent/integrations/__init__.py
seo_agent/integrations/pagespeed.py
seo_agent/integrations/search_console.py
tests/__init__.py
tests/test_agent.py
tests/test_audit_more.py
tests/test_baseline.py
tests/test_checks_extra.py
tests/test_config.py
tests/test_network.py
tests/test_registry.py
tests/test_reporting.py
tests/test_robots.py
seo_agent-0.4.0.dist-info/LICENSE
seo_agent-0.4.0.dist-info/METADATA
seo_agent-0.4.0.dist-info/WHEEL
seo_agent-0.4.0.dist-info/entry_points.txt
seo_agent-0.4.0.dist-info/top_level.txt
seo_agent-0.4.0.dist-info/RECORD
