Metadata-Version: 2.1
Name: seo-agent
Version: 0.4.0
Summary: Lightweight CLI that runs a technical SEO audit for a URL and outputs prioritized, actionable recommendations.
Author: Shubhendu Vaid
License: MIT License
Project-URL: Homepage, https://github.com/ShubhenduVaid/seo-agent
Project-URL: Source, https://github.com/ShubhenduVaid/seo-agent
Project-URL: Issues, https://github.com/ShubhenduVaid/seo-agent/issues
Project-URL: Documentation, https://github.com/ShubhenduVaid/seo-agent/tree/main/docs
Project-URL: Changelog, https://github.com/ShubhenduVaid/seo-agent/blob/main/CHANGELOG.md
Keywords: seo,technical seo,seo audit,site audit,website audit,crawl,crawler,search console,pagespeed,cli,python
Classifier: Development Status :: 3 - Alpha
Classifier: Intended Audience :: Developers
Classifier: Intended Audience :: Information Technology
Classifier: Programming Language :: Python
Classifier: Programming Language :: Python :: 3
Classifier: Programming Language :: Python :: 3 :: Only
Classifier: Programming Language :: Python :: 3.9
Classifier: Programming Language :: Python :: 3.10
Classifier: Programming Language :: Python :: 3.11
Classifier: Programming Language :: Python :: 3.12
Classifier: Topic :: Internet :: WWW/HTTP
Classifier: Topic :: Internet :: WWW/HTTP :: Site Management
Classifier: Topic :: Security
Classifier: Topic :: Utilities
Requires-Python: >=3.9
License-File: LICENSE
